voila_gridstack/__init__.py
voila_gridstack/_version.py
voila_gridstack/server_extension.py
voila_gridstack/config/jpserver-voila-gridstack.json
voila_gridstack/config/jupyter_config.json
voila_gridstack/config/nb-voila-gridstack.json
voila_gridstack/config/nbserver-voila-gridstack.json
voila_gridstack/nbextension/extension.js
voila_gridstack/nbextension/gridstack-jq.js
voila_gridstack/nbextension/voila-gridstack.css
voila_gridstack/nbextension/voila-gridstack.js
voila_gridstack/template/conf.json
voila_gridstack/template/gridstack.js.j2
voila_gridstack/template/gridstack_base.html.j2
voila_gridstack/template/index.html.j2
voila_gridstack/tests/conftest.py
voila_gridstack/tests/nb.ipynb
voila_gridstack/tests/nb_report.ipynb
voila_gridstack/tests/nb_without_metadata.ipynb
voila_gridstack/tests/test_empty_notebook.py
voila_gridstack/tests/test_notebook_metadata.py
voila_gridstack/tests/test_report_view.py
voila_gridstack/tests/test_resources.py
voila_gridstack/tests/test_templates.py
voila_gridstack/tests/voila.png
voila_gridstack-0.4.0.data/data/etc/jupyter/jupyter_notebook_config.d/nbserver-voila-gridstack.json
voila_gridstack-0.4.0.data/data/etc/jupyter/jupyter_server_config.d/jpserver-voila-gridstack.json
voila_gridstack-0.4.0.data/data/share/jupyter/nbextensions/voila-gridstack/extension.js
voila_gridstack-0.4.0.data/data/share/jupyter/nbextensions/voila-gridstack/gridstack-jq.js
voila_gridstack-0.4.0.data/data/share/jupyter/nbextensions/voila-gridstack/voila-gridstack.css
voila_gridstack-0.4.0.data/data/share/jupyter/nbextensions/voila-gridstack/voila-gridstack.js
voila_gridstack-0.4.0.data/data/etc/jupyter/nbconfig/notebook.d/nb-voila-gridstack.json
voila_gridstack-0.4.0.data/data/share/jupyter/labextensions/@voila-dashboards/jupyterlab-gridstack/package.json
voila_gridstack-0.4.0.data/data/share/jupyter/labextensions/@voila-dashboards/jupyterlab-gridstack/static/393.0bf937433b8593c0981f.js
voila_gridstack-0.4.0.dist-info/METADATA
voila_gridstack-0.4.0.dist-info/WHEEL
voila_gridstack-0.4.0.dist-info/licenses/LICENSE
voila_gridstack-0.4.0.dist-info/RECORD
