Metadata-Version: 2.1
Name: voila-gridstack
Version: 0.4.0
Project-URL: Homepage, https://github.com/voila-dashboards/voila-gridstack
Project-URL: Bug Tracker, https://github.com/voila-dashboards/voila-gridstack/issues
Project-URL: Repository, https://github.com/voila-dashboards/voila-gridstack
Author: Voila Development Team
License: BSD License
License-File: LICENSE
Classifier: Framework :: Jupyter
Classifier: Framework :: Jupyter :: JupyterLab
Classifier: Framework :: Jupyter :: JupyterLab :: 4
Classifier: Framework :: Jupyter :: JupyterLab :: Extensions
Classifier: Framework :: Jupyter :: JupyterLab :: Extensions :: Prebuilt
Classifier: License :: OSI Approved :: BSD License
Classifier: Programming Language :: Python
Classifier: Programming Language :: Python :: 3
Classifier: Programming Language :: Python :: 3.8
Classifier: Programming Language :: Python :: 3.9
Classifier: Programming Language :: Python :: 3.10
Classifier: Programming Language :: Python :: 3.11
Requires-Python: >=3.8
Requires-Dist: jupyterlab-widgets~=3.0
Requires-Dist: voila<0.6,>=0.2
Provides-Extra: dev
Requires-Dist: click; extra == 'dev'
Requires-Dist: hatch; extra == 'dev'
Requires-Dist: hatch-nodejs-version; extra == 'dev'
Requires-Dist: jupyter-releaser; extra == 'dev'
Provides-Extra: docs
Requires-Dist: myst-parser; extra == 'docs'
Requires-Dist: pydata-sphinx-theme; extra == 'docs'
Requires-Dist: sphinx; extra == 'docs'
Provides-Extra: test
Requires-Dist: bqplot; extra == 'test'
Requires-Dist: ipykernel; extra == 'test'
Requires-Dist: ipywidgets; extra == 'test'
Requires-Dist: lxml; extra == 'test'
Requires-Dist: matplotlib; extra == 'test'
Requires-Dist: nbconvert<8,>=6.4.5; extra == 'test'
Requires-Dist: numpy; extra == 'test'
Requires-Dist: pandas; extra == 'test'
Requires-Dist: pytest; extra == 'test'
Requires-Dist: pytest-tornasync; extra == 'test'
Requires-Dist: scipy; extra == 'test'
Requires-Dist: seaborn; extra == 'test'
